Metadata-Version: 2.1
Name: SHEPHARD
Version: 0.2.2
Summary: Python package for organizing large sets of protein data
Author-email: Alex Holehouse <alex.holehouse@wustl.edu>
License: MIT
Requires-Python: >=3.7
License-File: LICENSE
Requires-Dist: numpy
Requires-Dist: protfasta
Provides-Extra: test
Requires-Dist: pytest>=6.1.2; extra == "test"
